{
  "kendall_correlation": 0.358554326137681,
  "kendall_p_value": 1.661926808434916e-234,
  "peak_memory_mb": 4783,
  "system_level_score": 0.9755542504522535,
  "dataset_load_time": 7.23,
  "model_load_time": 78.0,
  "prediction_time": 103.16,
  "dataset_length": 4500,
  "output": "pruning_results/prune16layers_finetune6/",
  "lp": "en-de",
  "dataset": "RicardoRei/wmt-mqm-human-evaluation",
  "domain": "news",
  "year": 2022,
  "seed": 0,
  "n_gpus": 1,
  "batch_size": 8,
  "n_layers_to_prune": 16,
  "do_finetune": false,
  "model": "Unbabel/XCOMET-XL",
  "finetune_data_path": "data/mqm-spans-with-year-and-domain-but-no-news-2022.csv",
  "train_batch_size": 8,
  "grad_accum_steps": 16,
  "n_epochs": 1,
  "warmup_fraction": 0.1,
  "learning_rate": 0.0001,
  "n_calibration_batches": 2000,
  "use_cosine_similarity": false,
  "CUDA_VISIBLE_DEVICES": "5",
  "torch.version.cuda": "11.8",
  "torch.backends.cudnn.version()": 8700,
  "torch.cuda.nccl.version()": [
    2,
    18,
    6
  ]
}