{
  "kendall_correlation": 0.40860405885900736,
  "kendall_p_value": 7.951703515617553e-294,
  "peak_memory_mb": 16122,
  "samples_per_second": 14.239912457448007,
  "system_level_score": 0.951900345755948,
  "dataset_load_time": 4.59,
  "model_load_time": 562.96,
  "prediction_time": 316.01,
  "batch_size_time": 71.28,
  "dataset_length": 4500,
  "output": "speed_results/xl_4bits",
  "model": "Unbabel/XCOMET-XL",
  "onnx_path": null,
  "lp": "en-de",
  "dataset": "RicardoRei/wmt-mqm-human-evaluation",
  "domain": "news",
  "year": 2022,
  "seed": 0,
  "gpu": true,
  "half": false,
  "batch_size": 32,
  "prune_n_layers": 0,
  "quantize_n_bits": 4,
  "CUDA_VISIBLE_DEVICES": "3",
  "torch.version.cuda": "11.8",
  "torch.backends.cudnn.version()": 8700,
  "torch.cuda.nccl.version()": [
    2,
    18,
    6
  ]
}