{
  "kendall_correlation": 0.372011497575706,
  "kendall_p_value": 5.651746533225717e-76,
  "peak_memory_mb": 52254,
  "samples_per_second": 57.343990709815245,
  "system_level_score": 0.59269328542458,
  "dataset_load_time": 0.03,
  "model_load_time": 432.29,
  "prediction_time": 20.25,
  "batch_size_time": 111.54,
  "dataset_length": 1161,
  "output": "speed_results/a100_xl_3bits/",
  "model": "Unbabel/XCOMET-XL",
  "onnx_path": null,
  "lp": "en-zh",
  "dataset": "data/mt_en-zh_ground_truth_cleaned_l.tsv",
  "domain": "news",
  "year": 2022,
  "seed": 0,
  "gpu": true,
  "half": false,
  "batch_size": 128,
  "prune_n_layers": 0,
  "quantize_n_bits": 3,
  "CUDA_VISIBLE_DEVICES": "0",
  "torch.version.cuda": "12.1",
  "torch.backends.cudnn.version()": 8902,
  "torch.cuda.nccl.version()": [
    2,
    19,
    3
  ]
}