{
  "kendall_correlation": 0.4184922765887298,
  "kendall_p_value": 1.971619581631761e-117,
  "peak_memory_mb": 6854,
  "system_level_score": 0.9364575235885486,
  "dataset_load_time": 0.31,
  "model_load_time": 56.19,
  "prediction_time": 28.28,
  "dataset_length": 1425,
  "output": "pruning_results/prune04layers_finetune6/",
  "lp": "en-de",
  "dataset": "data/mt_en-de_ground_truth_cleaned_l.tsv",
  "domain": "news",
  "year": 2022,
  "seed": 0,
  "n_gpus": 1,
  "batch_size": 8,
  "n_layers_to_prune": 4,
  "do_finetune": false,
  "model": "Unbabel/XCOMET-XL",
  "CUDA_VISIBLE_DEVICES": "0",
  "torch.version.cuda": "11.8",
  "torch.backends.cudnn.version()": 8700,
  "torch.cuda.nccl.version()": [
    2,
    18,
    6
  ]
}